typed_coinbaseinternational/__init__.py
typed_coinbaseinternational-0.1.0.dist-info/METADATA
typed_coinbaseinternational-0.1.0.dist-info/WHEEL
typed_coinbaseinternational-0.1.0.dist-info/top_level.txt
typed_coinbaseinternational-0.1.0.dist-info/RECORD
